malemba/__init__.py
malemba/constants.py
malemba/ds_tools.py
malemba/model_base.py
malemba/model_scheme.py
malemba/regressor_base.py
malemba/dastruc/__init__.py
malemba/dastruc/data_pool.py
malemba/dastruc/generators.py
malemba/dastruc/readers.py
MaLeMBa-0.4.14.dist-info/LICENSE
MaLeMBa-0.4.14.dist-info/METADATA
MaLeMBa-0.4.14.dist-info/WHEEL
MaLeMBa-0.4.14.dist-info/entry_points.txt
MaLeMBa-0.4.14.dist-info/top_level.txt
MaLeMBa-0.4.14.dist-info/RECORD
