Metadata-Version: 2.1
Name: MaLeMBa
Version: 0.4.14
Summary: Machine Learning Models Base
Home-page: https://github.com/loven-doo/MaLeMBa
Author: Denis Moshensky
Author-email: loven7doo@gmail.com
License: UNKNOWN
Platform: UNKNOWN
Classifier: Programming Language :: Python :: 3
Classifier: License :: OSI Approved :: BSD License
Classifier: Operating System :: OS Independent
Requires-Dist: numpy (>=1.15.1)
Requires-Dist: pandas (>=0.23.4)
Requires-Dist: scipy (>=1.1.0)
Requires-Dist: shared-ndarray (>=1.1.1)
Requires-Dist: jsondler (>=0.0.1)
